grokcore.site-4.1-py3.12-nspkg.pth
grokcore/site/__init__.py
grokcore/site/components.py
grokcore/site/configure.zcml
grokcore/site/directive.py
grokcore/site/ftesting.zcml
grokcore/site/interfaces.py
grokcore/site/meta.py
grokcore/site/meta.zcml
grokcore/site/subscriber.py
grokcore/site/testing.py
grokcore/site/util.py
grokcore/site/tests/__init__.py
grokcore/site/tests/test_base.py
grokcore/site/tests/test_functional.py
grokcore/site/tests/base/__init__.py
grokcore/site/tests/base/application/__init__.py
grokcore/site/tests/base/application/application.py
grokcore/site/tests/base/utility/local_implementsnone_fixture.py
grokcore/site/tests/functional/__init__.py
grokcore/site/tests/functional/application/__init__.py
grokcore/site/tests/functional/application/application.py
grokcore/site/tests/functional/site/__init__.py
grokcore/site/tests/functional/site/site.py
grokcore/site/tests/functional/utility/__init__.py
grokcore/site/tests/functional/utility/install_on.py
grokcore/site/tests/functional/utility/local.py
grokcore/site/tests/functional/utility/local_override.py
grokcore/site/tests/functional/utility/public.py
grokcore/site/tests/functional/utility/subclass.py
grokcore_site-4.1.dist-info/licenses/LICENSE.txt
grokcore_site-4.1.dist-info/METADATA
grokcore_site-4.1.dist-info/WHEEL
grokcore_site-4.1.dist-info/namespace_packages.txt
grokcore_site-4.1.dist-info/top_level.txt
grokcore_site-4.1.dist-info/RECORD
