Metadata-Version: 2.4
Name: grokcore.site
Version: 4.1
Summary: Grok-like configuration for Zope local site and utilities
Home-page: https://github.com/zopefoundation/grokcore.site
Author: Grok Team
Author-email: zope-dev@zope.dev
License: ZPL
Classifier: Environment :: Web Environment
Classifier: Framework :: Zope :: 3
Classifier: Intended Audience :: Developers
Classifier: License :: OSI Approved :: Zope Public License
Classifier: Programming Language :: Python :: 3
Classifier: Programming Language :: Python :: 3.9
Classifier: Programming Language :: Python :: 3.10
Classifier: Programming Language :: Python :: 3.11
Classifier: Programming Language :: Python :: 3.12
Classifier: Programming Language :: Python :: 3.13
Classifier: Programming Language :: Python :: Implementation :: CPython
Classifier: Programming Language :: Python :: Implementation :: PyPy
Classifier: Programming Language :: Python
Requires-Python: >=3.9
License-File: LICENSE.txt
Requires-Dist: setuptools
Requires-Dist: grokcore.component>=2.1
Requires-Dist: martian>=0.13
Requires-Dist: persistent
Requires-Dist: zope.annotation
Requires-Dist: zope.component
Requires-Dist: zope.container
Requires-Dist: zope.event
Requires-Dist: zope.interface
Requires-Dist: zope.lifecycleevent
Requires-Dist: zope.schema
Requires-Dist: zope.site>=4.4
Provides-Extra: test
Requires-Dist: zope.app.appsetup; extra == "test"
Requires-Dist: zope.component; extra == "test"
Requires-Dist: zope.configuration; extra == "test"
Requires-Dist: zope.testing; extra == "test"
Requires-Dist: grokcore.content; extra == "test"
Dynamic: author
Dynamic: author-email
Dynamic: classifier
Dynamic: description
Dynamic: home-page
Dynamic: license
Dynamic: license-file
Dynamic: provides-extra
Dynamic: requires-dist
Dynamic: requires-python
Dynamic: summary
